podlocalsync.py
podlocalsync-0.0.1.dist-info/entry_points.txt
podlocalsync-0.0.1.dist-info/LICENSE
podlocalsync-0.0.1.dist-info/WHEEL
podlocalsync-0.0.1.dist-info/METADATA
podlocalsync-0.0.1.dist-info/RECORD
