Metadata-Version: 2.1
Name: podlocalsync
Version: 0.0.1
Summary: Manage and serve podcast RSS feeds locally
License: GPL-3.0-only
Author: Toby Fleming
Author-email: tobywf@users.noreply.github.com
Requires-Python: >=3.8,<4.0
Classifier: Development Status :: 2 - Pre-Alpha
Classifier: License :: OSI Approved :: GNU General Public License v3 (GPLv3)
Classifier: Natural Language :: English
Classifier: Operating System :: OS Independent
Classifier: Programming Language :: Python :: 3
Classifier: Programming Language :: Python :: 3 :: Only
Classifier: Programming Language :: Python :: 3.8
Classifier: Programming Language :: Python :: 3.9
Requires-Dist: cleo (>=0.8.1,<0.9.0)
Requires-Dist: lxml (>=4.5.2,<5.0.0)
Requires-Dist: toml (>=0.10.1,<0.11.0)
